odoo/addons/web_widget_image_download/README.rst
odoo/addons/web_widget_image_download/__init__.py
odoo/addons/web_widget_image_download/__manifest__.py
odoo/addons/web_widget_image_download/i18n/es.po
odoo/addons/web_widget_image_download/i18n/hr.po
odoo/addons/web_widget_image_download/i18n/it.po
odoo/addons/web_widget_image_download/i18n/lt.po
odoo/addons/web_widget_image_download/i18n/nl_NL.po
odoo/addons/web_widget_image_download/i18n/pt.po
odoo/addons/web_widget_image_download/i18n/web_widget_image_download.pot
odoo/addons/web_widget_image_download/i18n/zh_CN.po
odoo/addons/web_widget_image_download/readme/CONTRIBUTORS.md
odoo/addons/web_widget_image_download/readme/DESCRIPTION.md
odoo/addons/web_widget_image_download/readme/USAGE.md
odoo/addons/web_widget_image_download/static/description/icon.png
odoo/addons/web_widget_image_download/static/description/index.html
odoo/addons/web_widget_image_download/static/src/components/image_field.esm.js
odoo/addons/web_widget_image_download/static/src/xml/web_widget_image_download.xml
odoo_addon_web_widget_image_download-17.0.1.0.0.2.dist-info/METADATA
odoo_addon_web_widget_image_download-17.0.1.0.0.2.dist-info/WHEEL
odoo_addon_web_widget_image_download-17.0.1.0.0.2.dist-info/top_level.txt
odoo_addon_web_widget_image_download-17.0.1.0.0.2.dist-info/RECORD
