Metadata-Version: 2.1
Name: odoo-addon-web_widget_image_download
Version: 17.0.1.0.0.2
Requires-Python: >=3.10
Requires-Dist: odoo>=17.0a,<17.1dev
Summary: Allows to download any image from its widget
Home-page: https://github.com/OCA/web
License: LGPL-3
Author: Tecnativa, Odoo Community Association (OCA), Kaushal Prajapati
Author-email: support@odoo-community.org
Classifier: Programming Language :: Python
Classifier: Framework :: Odoo
Classifier: Framework :: Odoo :: 17.0
Classifier: License :: OSI Approved :: GNU Lesser General Public License v3 (LGPLv3)
